pfatools/__init__.py
pfatools/random_person/__init__.py
pfatools/utils/__init__.py
pfatools-0.1.2.dist-info/WHEEL
pfatools-0.1.2.dist-info/METADATA
pfatools-0.1.2.dist-info/RECORD
