Metadata-Version: 2.1
Name: pfatools
Version: 0.1.2
Summary: Collection of tools used for teaching python through API requests and data exploration.
License: MIT
Author: msherburne
Author-email: mathieusherburne@outlook.com
Requires-Python: >=3.8,<4.0
Classifier: License :: OSI Approved :: MIT License
Classifier: Programming Language :: Python :: 3
Classifier: Programming Language :: Python :: 3.10
Classifier: Programming Language :: Python :: 3.8
Classifier: Programming Language :: Python :: 3.9
Requires-Dist: requests (>=2.28.1,<3.0.0)
